python_flint-0.8.0.dist-info/RECORD
python_flint-0.8.0.dist-info/LICENSE
python_flint-0.8.0.dist-info/WHEEL
python_flint-0.8.0.dist-info/METADATA
flint/__init__.py
flint/pyflint.cpython-313t-darwin.so
flint/py.typed
flint/typing.py
flint/types/fmpq_mpoly.cpython-313t-darwin.so
flint/types/fmpz_poly.pyi
flint/types/fmpz_mod_mat.cpython-313t-darwin.so
flint/types/fmpq_poly.pyi
flint/types/dirichlet.cpython-313t-darwin.so
flint/types/arb_mat.cpython-313t-darwin.so
flint/types/fq_default_poly.pyi
flint/types/acb_theta.cpython-313t-darwin.so
flint/types/acb_series.cpython-313t-darwin.so
flint/types/fmpz_mod_mpoly.pyi
flint/types/fq_default_poly.cpython-313t-darwin.so
flint/types/nmod_mpoly.pyi
flint/types/fmpz_mpoly.pyi
flint/types/fmpq_series.cpython-313t-darwin.so
flint/types/fmpz_mpoly.cpython-313t-darwin.so
flint/types/nmod.pyi
flint/types/nmod_mpoly.cpython-313t-darwin.so
flint/types/fmpq.pyi
flint/types/arb_series.cpython-313t-darwin.so
flint/types/__init__.py
flint/types/fq_default.cpython-313t-darwin.so
flint/types/fmpq_mpoly.pyi
flint/types/fmpq_series.pyi
flint/types/fmpz_mod.pyi
flint/types/fmpz_mod_poly.cpython-313t-darwin.so
flint/types/nmod_mat.cpython-313t-darwin.so
flint/types/nmod_poly.cpython-313t-darwin.so
flint/types/fmpz_series.cpython-313t-darwin.so
flint/types/fmpq_poly.cpython-313t-darwin.so
flint/types/fq_default.pyi
flint/types/arf.cpython-313t-darwin.so
flint/types/acb_poly.cpython-313t-darwin.so
flint/types/acb.cpython-313t-darwin.so
flint/types/nmod.cpython-313t-darwin.so
flint/types/arb_poly.cpython-313t-darwin.so
flint/types/fmpz_series.pyi
flint/types/arb.cpython-313t-darwin.so
flint/types/fmpz.cpython-313t-darwin.so
flint/types/fmpz.pyi
flint/types/_gr.cpython-313t-darwin.so
flint/types/fmpq.cpython-313t-darwin.so
flint/types/fmpz_mat.cpython-313t-darwin.so
flint/types/fmpq_vec.cpython-313t-darwin.so
flint/types/acb_mat.cpython-313t-darwin.so
flint/types/fmpz_mod.cpython-313t-darwin.so
flint/types/nmod_poly.pyi
flint/types/fmpz_vec.cpython-313t-darwin.so
flint/types/fmpz_mod_mpoly.cpython-313t-darwin.so
