Metadata-Version: 2.1
Name: python-flint
Version: 0.8.0
Summary: Bindings for FLINT
Author-Email: Fredrik Johansson <fredrik.johansson@gmail.com>, Oscar Benjamin <oscar.j.benjamin@gmail.com>
License: MIT License
Classifier: Topic :: Scientific/Engineering :: Mathematics
Project-URL: Homepage, https://github.com/flintlib/python-flint
Project-URL: Documentation, https://python-flint.readthedocs.io/en/latest/
Project-URL: Repository, https://github.com/flintlib/python-flint
Project-URL: Changelog, https://github.com/flintlib/python-flint/blob/master/README.md#changelog
Requires-Python: >=3.11
